LICENSE
MANIFEST.in
README.md
setup.py
django_ios_notifications.egg-info/PKG-INFO
django_ios_notifications.egg-info/SOURCES.txt
django_ios_notifications.egg-info/dependency_links.txt
django_ios_notifications.egg-info/not-zip-safe
django_ios_notifications.egg-info/requires.txt
django_ios_notifications.egg-info/top_level.txt
ios_notifications/__init__.py
ios_notifications/admin.py
ios_notifications/api.py
ios_notifications/decorators.py
ios_notifications/exceptions.py
ios_notifications/forms.py
ios_notifications/http.py
ios_notifications/models.py
ios_notifications/settings.py
ios_notifications/test.pem
ios_notifications/tests.py
ios_notifications/urls.py
ios_notifications/utils.py
ios_notifications/management/__init__.py
ios_notifications/management/__init__.pyc
ios_notifications/management/commands/__init__.py
ios_notifications/management/commands/__init__.pyc
ios_notifications/management/commands/call_feedback_service.py
ios_notifications/management/commands/push_ios_notification.py
ios_notifications/management/commands/push_ios_notification.pyc
ios_notifications/migrations/0001_initial.py
ios_notifications/migrations/0002_auto__add_field_notification_custom_payload__chg_field_notification_so.py
ios_notifications/migrations/0003_auto__add_field_notification_loc_payload.py
ios_notifications/migrations/0004_auto__add_field_notification_silent.py
ios_notifications/migrations/__init__.py
ios_notifications/templates/admin/ios_notifications/notification/change_form.html
ios_notifications/templates/admin/ios_notifications/notification/push_notification.html