Metadata-Version: 1.1
Name: django-ios-notifications
Version: 0.2.0
Summary: Django iOS Notifications makes it easy to send push notifications to iOS devices
Home-page: https://github.com/stephenmuss/django-ios-notifications
Author: Stephen Muss
Author-email: stephenmuss@gmail.com
License: BSD License
Download-URL: https://github.com/stephenmuss/django-ios-notifications/zipball/v0.2.0
Platform: UNKNOWN
Classifier: Environment :: Web Environment
Classifier: Framework :: Django
Classifier: Intended Audience :: Developers
Classifier: License :: OSI Approved :: BSD License
Classifier: Operating System :: OS Independent
Classifier: Programming Language :: Python
Classifier: Topic :: Software Development :: Libraries :: Application Frameworks
